LICENSE
MANIFEST.in
README.rst
requirements-dev.txt
requirements.txt
setup.py
bert/__init__.py
bert/attention.py
bert/embeddings.py
bert/layer.py
bert/loader.py
bert/loader_albert.py
bert/model.py
bert/transformer.py
bert/version.py
bert/tokenization/__init__.py
bert/tokenization/albert_tokenization.py
bert/tokenization/bert_tokenization.py
bert_for_tf2_mod.egg-info/PKG-INFO
bert_for_tf2_mod.egg-info/SOURCES.txt
bert_for_tf2_mod.egg-info/dependency_links.txt
bert_for_tf2_mod.egg-info/requires.txt
bert_for_tf2_mod.egg-info/top_level.txt
bert_for_tf2_mod.egg-info/zip-safe
tests/ext/__init__.py
tests/ext/modeling.py
tests/nonci/__init__.py
tests/nonci/test_attention.py
tests/nonci/test_bert.py
tests/nonci/test_compare_pretrained.py
tests/nonci/test_load_pretrained_weights.py
tests/nonci/test_multi_lang.py
tests/nonci/test_stock_weights.py
tests/nonci/test_transformer.py