Metadata-Version: 2.1
Name: bert-for-tf2-mod
Version: 0.14.10
Summary: A TensorFlow 2.x Keras implementation of BERT.
Home-page: https://github.com/kpe/bert-for-tf2/
Author: kpe
Author-email: kpe.git@gmailbox.org
License: MIT
Keywords: tensorflow keras bert
Platform: UNKNOWN
Classifier: Development Status :: 5 - Production/Stable
Classifier: License :: OSI Approved :: MIT License
Classifier: Programming Language :: Python
Classifier: Programming Language :: Python :: 3
Classifier: Programming Language :: Python :: 3.5
Classifier: Programming Language :: Python :: 3.6
Classifier: Programming Language :: Python :: 3.7
Classifier: Programming Language :: Python :: Implementation :: CPython
Classifier: Programming Language :: Python :: Implementation :: PyPy
Requires-Python: >=3.5
